lldbvis/__init__.py
lldbvis/__main__.py
lldbvis/debug.py
lldbvis/demo/__init__.py
lldbvis/events/__init__.py
lldbvis/events/dispatcher.py
lldbvis/events/input.py
lldbvis/events/signals.py
lldbvis/gui/__init__.py
lldbvis/gui/widgets/__init__.py
lldbvis/gui/widgets/command_widget.py
lldbvis/gui/widgets/console_widget.py
lldbvis/gui/widgets/editors.py
lldbvis/gui/widgets/frames_widget.py
lldbvis/gui/widgets/variable_widget.py
lldbvis/gui/widgets/vis_widget.py
lldbvis/gui/windows/__init__.py
lldbvis/gui/windows/main_window.py
lldbvis/icons/__init__.py
lldbvis/icons/pause.svg
lldbvis/icons/play.svg
lldbvis/icons/step_instruction.ico
lldbvis/icons/step_into.ico
lldbvis/icons/step_out.ico
lldbvis/icons/step_out_of_frame.ico
lldbvis/icons/step_over.ico
lldbvis/icons/stop.svg
lldbvis/meta/__init__.py
lldbvis/meta/meta_classes.py
lldbvis/settings/__init__.py
lldbvis/settings/constants.py
lldbvis/settings/enums.py
lldbvis/tree/__init__.py
lldbvis/tree/label.py
lldbvis/tree/layouts.py
lldbvis/tree/node.py
lldbvis/tree/node_data.py
lldbvis/tree/node_geom.py
lldbvis/util/__init__.py
lldbvis/util/bpl.py
lldbvis/util/camera.py
lldbvis/util/colors.py
lldbvis/util/enums.py
lldbvis/util/formatters.py
lldbvis/util/light.py
lldbvis/util/log.py
lldbvis/util/material.py
lldbvis/util/transform.py
lldbvis/util/vectors.py
lldbvis-0.0.6.dist-info/LICENSE
lldbvis-0.0.6.dist-info/METADATA
lldbvis-0.0.6.dist-info/WHEEL
lldbvis-0.0.6.dist-info/entry_points.txt
lldbvis-0.0.6.dist-info/top_level.txt
lldbvis-0.0.6.dist-info/RECORD
